djtokit/__init__.py
djtokit/ctx/__init__.py
djtokit/ctx/context.py
djtokit/ctx/ctx_middleware.py
djtokit/custom_db/__init__.py
djtokit/custom_db/manager.py
djtokit/custom_db/mysql/__init__.py
djtokit/custom_db/mysql/base.py
djtokit/custom_db/router/__init__.py
djtokit/custom_db/router/bigdata.py
djtokit/custom_db/router/rw.py
djtokit/dbusing/__init__.py
djtokit-0.1.1.dist-info/WHEEL
djtokit-0.1.1.dist-info/METADATA
djtokit-0.1.1.dist-info/RECORD
